dootask/__init__.py
dootask/client.py
dootask/exceptions.py
dootask/models.py
dootask_tools-0.0.7.dist-info/licenses/LICENSE
dootask_tools-0.0.7.dist-info/METADATA
dootask_tools-0.0.7.dist-info/WHEEL
dootask_tools-0.0.7.dist-info/top_level.txt
dootask_tools-0.0.7.dist-info/RECORD
