Metadata-Version: 2.4
Name: dootask-tools
Version: 0.0.7
Summary: DooTask Tools 客户端库
Home-page: https://github.com/dootask/dootask-tools
Author: DooTask Team
Author-email: support@dootask.com
Project-URL: Bug Reports, https://github.com/dootask/dootask-tools/issues
Project-URL: Source, https://github.com/dootask/dootask-tools
Project-URL: Documentation, https://github.com/dootask/dootask-tools#readme
Keywords: dootask api client chat project management collaboration
Classifier: Development Status :: 5 - Production/Stable
Classifier: Intended Audience :: Developers
Classifier: License :: OSI Approved :: MIT License
Classifier: Operating System :: OS Independent
Classifier: Programming Language :: Python :: 3
Classifier: Programming Language :: Python :: 3.7
Classifier: Programming Language :: Python :: 3.8
Classifier: Programming Language :: Python :: 3.9
Classifier: Programming Language :: Python :: 3.10
Classifier: Programming Language :: Python :: 3.11
Classifier: Programming Language :: Python :: 3.12
Classifier: Topic :: Software Development :: Libraries :: Python Modules
Classifier: Topic :: Communications :: Chat
Classifier: Topic :: Office/Business :: Groupware
Classifier: Topic :: Internet :: WWW/HTTP :: Dynamic Content
Requires-Python: >=3.7
License-File: LICENSE
Requires-Dist: requests>=2.28.0
Requires-Dist: dataclasses>=0.8; python_version < "3.7"
Dynamic: author
Dynamic: author-email
Dynamic: classifier
Dynamic: description
Dynamic: description-content-type
Dynamic: home-page
Dynamic: keywords
Dynamic: license-file
Dynamic: project-url
Dynamic: requires-dist
Dynamic: requires-python
Dynamic: summary
